Metadata-Version: 2.1
Name: BetterLoader
Version: 0.2.1
Summary: A better PyTorch dataloader
Home-page: https://github.com/BinItAI/BetterLoader
Author: BinIt Inc
Author-email: support@binit.in
License: MIT
Download-URL: https://github.com/BinItAI/BetterLoader/archive/0.1.5.zip
Platform: UNKNOWN
Classifier: Development Status :: 3 - Alpha
Classifier: Intended Audience :: Science/Research
Classifier: License :: OSI Approved :: MIT License
Classifier: Operating System :: POSIX :: Linux
Classifier: Operating System :: MacOS :: MacOS X
Classifier: Operating System :: Microsoft :: Windows :: Windows 10
Classifier: Programming Language :: Python :: 3.7
